MANIFEST.in
README.md
setup.py
qtc/__init__.py
qtc/env_config.cfg
qtc/env_config.py
qtc/version.py
qtc.egg-info/PKG-INFO
qtc.egg-info/SOURCES.txt
qtc.egg-info/dependency_links.txt
qtc.egg-info/not-zip-safe
qtc.egg-info/requires.txt
qtc.egg-info/top_level.txt
qtc/app_configs/__init__.py
qtc/app_configs/bq/__init__.py
qtc/app_configs/bq/constants.py
qtc/app_configs/bq/params.py
qtc/app_configs/bq_sim/__init__.py
qtc/app_configs/bq_sim/params.py
qtc/calendar/__init__.py
qtc/calendar/calendar.py
qtc/calendar/cn_stock_calendar.py
qtc/consts/__init__.py
qtc/consts/enums.py
qtc/consts/static.py
qtc/data/__init__.py
qtc/data/sec.py
qtc/data/dal/__init__.py
qtc/data/dal/calendar.py
qtc/data/dal/sec.py
qtc/data/dal/common/__init__.py
qtc/data/dal/common/sql_compiler.py
qtc/ext/__init__.py
qtc/ext/configurable.py
qtc/ext/enum.py
qtc/ext/inspect.py
qtc/ext/logging.py
qtc/ext/multiprocessing.py
qtc/ext/unittest.py
qtc/file/__init__.py
qtc/file/file_cache.py
qtc/file/file_manager.py
qtc/file/file_serialization.py
qtc/toolbox/__init__.py
qtc/toolbox/calcs.py
qtc/toolbox/dataframe.py
qtc/utils/__init__.py
qtc/utils/cipher_utils.py
qtc/utils/dash_utils.py
qtc/utils/datetime_utils.py
qtc/utils/db_utils.py
qtc/utils/email_utils.py
qtc/utils/endpoint_utils.py
qtc/utils/file_system_utils.py
qtc/utils/html_utils.py
qtc/utils/misc_utils.py
qtc/utils/notebook_utils.py
tests/__init__.py
tests/test_env_config.py
tests/ext/__init__.py
tests/ext/test_enum.py
tests/ext/test_inspect.py
tests/file/__init__.py
tests/file/test_file_cache.py
tests/file/test_file_manager.py
tests/file/test_file_serialization.py
tests/utils/__init__.py
tests/utils/test_cipher_utils.py
tests/utils/test_datetime_utils.py
tests/utils/test_db_utils.py
tests/utils/test_misc_utils.py