Metadata-Version: 2.1
Name: qtc
Version: 0.0.9
Summary: Quant Trading
Home-page: 
Author: Andrew Hu
Author-email: AndrewWeiHu@gmail.com
Platform: any
